fjud_mcp/__init__.py
fjud_mcp/crawler.py
fjud_mcp/server.py
fjud_mcp-1.1.0.dist-info/METADATA
fjud_mcp-1.1.0.dist-info/WHEEL
fjud_mcp-1.1.0.dist-info/entry_points.txt
fjud_mcp-1.1.0.dist-info/licenses/LICENSE
fjud_mcp-1.1.0.dist-info/RECORD
