Metadata-Version: 2.4
Name: fjud-mcp
Version: 1.1.0
Summary: Taiwan Judicial Yuan judgment search MCP server
Project-URL: Homepage, https://github.com/your-username/fjud-mcp
Project-URL: Repository, https://github.com/your-username/fjud-mcp.git
Project-URL: Issues, https://github.com/your-username/fjud-mcp/issues
Author-email: Claude Code Assistant <noreply@anthropic.com>
License-Expression: MIT
License-File: LICENSE
Keywords: crawler,judgment,judicial,legal,mcp,taiwan
Classifier: Development Status :: 4 - Beta
Classifier: Intended Audience :: Developers
Classifier: Intended Audience :: Legal Industry
Classifier: License :: OSI Approved :: MIT License
Classifier: Programming Language :: Python :: 3
Classifier: Programming Language :: Python :: 3.8
Classifier: Programming Language :: Python :: 3.9
Classifier: Programming Language :: Python :: 3.10
Classifier: Programming Language :: Python :: 3.11
Classifier: Programming Language :: Python :: 3.12
Classifier: Topic :: Internet :: WWW/HTTP :: Indexing/Search
Classifier: Topic :: Software Development :: Libraries :: Python Modules
Classifier: Topic :: Text Processing :: Linguistic
Requires-Python: >=3.8
Requires-Dist: beautifulsoup4>=4.9.0
Requires-Dist: fastmcp>=0.2.0
Requires-Dist: lxml>=4.6.0
Requires-Dist: pydantic>=2.0.0
Requires-Dist: requests>=2.25.0
Provides-Extra: dev
Requires-Dist: black; extra == 'dev'
Requires-Dist: build; extra == 'dev'
Requires-Dist: flake8; extra == 'dev'
Requires-Dist: isort; extra == 'dev'
Requires-Dist: pytest; extra == 'dev'
Requires-Dist: pytest-asyncio; extra == 'dev'
Requires-Dist: twine; extra == 'dev'
